mkrexx/__init__.py
mkrexx/__main__.py
mkrexx/utilities/__init__.py
mkrexx/utilities/background_colors.py
mkrexx/utilities/file_system_manager.py
mkrexx/utilities/logger.py
mkrexx-0.7.2.dist-info/LICENSE
mkrexx-0.7.2.dist-info/METADATA
mkrexx-0.7.2.dist-info/WHEEL
mkrexx-0.7.2.dist-info/top_level.txt
mkrexx-0.7.2.dist-info/RECORD
