Metadata-Version: 2.1
Name: mkrexx
Version: 0.7.2
Summary: Python library that leverage include statements in rexx files for the build process.
Home-page: UNKNOWN
Author: Guilherme Cartier
License: UNKNOWN
Platform: UNKNOWN
Requires-Python: >=3.6
Requires-Dist: pyrexx
Requires-Dist: python-decouple
